agent_a/__init__.py
agent_a/agent.py
agent_a/args.py
agent_a/config.py
agent_a/install_upgrade.py
agent_a/prompts.py
agent_a/tui.py
agent_a/utils.py
agent_a/workflows.py
agent_a/files/__init__.py
agent_a/files/agent_a.sh
agent_a/files/user_agent_a.json
agent_a/files/prompts/__init__.py
agent_a/files/prompts/coding.txt
agent_a/files/prompts/documentation.txt
agent_a/files/prompts/general.txt
agent_a/files/prompts/plain_text_guide.txt
agent_a/files/prompts/software_solution_architect_prompt.txt
agent_a/files/prompts/technical_implementation_planner.txt
agent_a/files/scripts/__init__.py
agent_a/files/scripts/a
agent_a/files/scripts/lwc
agent_a/providers/__init__.py
agent_a/providers/base.py
agent_a/providers/claude.py
agent_a/providers/factory.py
agent_a/providers/gemini.py
agent_a_ai-0.0.1.dist-info/licenses/LICENSE.txt
agent_a_ai-0.0.1.dist-info/METADATA
agent_a_ai-0.0.1.dist-info/WHEEL
agent_a_ai-0.0.1.dist-info/entry_points.txt
agent_a_ai-0.0.1.dist-info/top_level.txt
agent_a_ai-0.0.1.dist-info/RECORD
