Metadata-Version: 2.4
Name: agent_a_ai
Version: 0.0.1
Summary: AI Agent: Agent A
Author-email: Mark Schiffl <rnghack@gmail.com>
License: Apache-2.0
Classifier: Programming Language :: Python :: 3
Classifier: Operating System :: OS Independent
Requires-Python: >=3.8
License-File: LICENSE.txt
Requires-Dist: importlib-resources; python_version < "3.9"
Requires-Dist: anthropic>=0.69.0
Requires-Dist: google-genai>=1.38.0
Dynamic: license-file
